context_relaxer/__init__.py
context_relaxer/_api.py
context_relaxer/py.typed
context_relaxer-0.1.4.dist-info/licenses/LICENSE
context_relaxer-0.1.4.dist-info/METADATA
context_relaxer-0.1.4.dist-info/WHEEL
context_relaxer-0.1.4.dist-info/top_level.txt
context_relaxer-0.1.4.dist-info/RECORD
