Metadata-Version: 2.4
Name: context-relaxer
Version: 0.1.4
Summary: Relax python default SSL Context verification flags
Author-email: Yehuda Deutsch <yeh@uda.co.il>
License-Expression: MIT
Project-URL: Repository, https://gitlab.com/uda/context-relaxer.git
Project-URL: Issues, https://gitlab.com/uda/context-relaxer/-/issues
Classifier: Development Status :: 5 - Production/Stable
Classifier: Intended Audience :: Developers
Classifier: Operating System :: OS Independent
Classifier: Programming Language :: Python :: 3 :: Only
Classifier: Programming Language :: Python :: 3
Classifier: Programming Language :: Python :: 3.10
Classifier: Programming Language :: Python :: 3.11
Classifier: Programming Language :: Python :: 3.12
Classifier: Programming Language :: Python :: 3.13
Classifier: Programming Language :: Python :: 3.14
Classifier: Topic :: Internet :: WWW/HTTP
Classifier: Topic :: Security
Requires-Python: >=3.10
License-File: LICENSE
Dynamic: license-file
